stackit/runcommand/__init__.py
stackit/runcommand/api/__init__.py
stackit/runcommand/api/default_api.py
stackit/runcommand/api_client.py
stackit/runcommand/api_response.py
stackit/runcommand/configuration.py
stackit/runcommand/exceptions.py
stackit/runcommand/models/__init__.py
stackit/runcommand/models/command_details.py
stackit/runcommand/models/command_template.py
stackit/runcommand/models/command_template_response.py
stackit/runcommand/models/command_template_schema.py
stackit/runcommand/models/commands.py
stackit/runcommand/models/create_command_payload.py
stackit/runcommand/models/error_response.py
stackit/runcommand/models/get_commands_response.py
stackit/runcommand/models/model_field.py
stackit/runcommand/models/new_command_response.py
stackit/runcommand/models/parameters_schema.py
stackit/runcommand/models/properties.py
stackit/runcommand/py.typed
stackit/runcommand/rest.py
stackit_runcommand-1.1.1.dist-info/METADATA
stackit_runcommand-1.1.1.dist-info/WHEEL
stackit_runcommand-1.1.1.dist-info/licenses/LICENSE.md
stackit_runcommand-1.1.1.dist-info/licenses/NOTICE.txt
stackit_runcommand-1.1.1.dist-info/RECORD
